[
  { "term": "das Essen", "translation": "food; meal", "phonetic": "ˈɛsn̩", "metadata": { "gender": "neuter", "plural": "Essen", "pos": "noun" } },
  { "term": "das Wasser", "translation": "water", "phonetic": "ˈvasɐ", "metadata": { "gender": "neuter", "plural": "Wässer", "pos": "noun" } },
  { "term": "das Brot", "translation": "bread", "phonetic": "bʁoːt", "metadata": { "gender": "neuter", "plural": "Brote", "pos": "noun" } },
  { "term": "der Kaffee", "translation": "coffee", "phonetic": "ˈkafe", "metadata": { "gender": "masculine", "plural": "Kaffees", "pos": "noun" } },
  { "term": "der Tee", "translation": "tea", "phonetic": "teː", "metadata": { "gender": "masculine", "plural": "Tees", "pos": "noun" } },
  { "term": "die Milch", "translation": "milk", "phonetic": "mɪlç", "metadata": { "gender": "feminine", "plural": "—", "pos": "noun" } },
  { "term": "der Apfel", "translation": "apple", "phonetic": "ˈap͡fl̩", "metadata": { "gender": "masculine", "plural": "Äpfel", "pos": "noun" } },
  { "term": "die Banane", "translation": "banana", "phonetic": "baˈnaːnə", "metadata": { "gender": "feminine", "plural": "Bananen", "pos": "noun" } },
  { "term": "das Ei", "translation": "egg", "phonetic": "aɪ", "metadata": { "gender": "neuter", "plural": "Eier", "pos": "noun" } },
  { "term": "der Käse", "translation": "cheese", "phonetic": "ˈkɛːzə", "metadata": { "gender": "masculine", "plural": "Käse", "pos": "noun" } },
  { "term": "das Fleisch", "translation": "meat", "phonetic": "flaɪʃ", "metadata": { "gender": "neuter", "plural": "—", "pos": "noun" } },
  { "term": "der Fisch", "translation": "fish", "phonetic": "fɪʃ", "metadata": { "gender": "masculine", "plural": "Fische", "pos": "noun" } },
  { "term": "das Gemüse", "translation": "vegetables", "phonetic": "ɡəˈmyːzə", "metadata": { "gender": "neuter", "plural": "Gemüse", "pos": "noun" } },
  { "term": "das Obst", "translation": "fruit", "phonetic": "oːpst", "metadata": { "gender": "neuter", "plural": "—", "pos": "noun" } },
  { "term": "der Zucker", "translation": "sugar", "phonetic": "ˈtsʊkɐ", "metadata": { "gender": "masculine", "plural": "—", "pos": "noun" } },
  { "term": "das Salz", "translation": "salt", "phonetic": "zalts", "metadata": { "gender": "neuter", "plural": "Salze", "pos": "noun" } },
  { "term": "das Bier", "translation": "beer", "phonetic": "biːɐ̯", "metadata": { "gender": "neuter", "plural": "Biere", "pos": "noun" } },
  { "term": "der Wein", "translation": "wine", "phonetic": "vaɪn", "metadata": { "gender": "masculine", "plural": "Weine", "pos": "noun" } },
  { "term": "das Frühstück", "translation": "breakfast", "phonetic": "ˈfʁyːʃtʏk", "metadata": { "gender": "neuter", "plural": "Frühstücke", "pos": "noun" } },
  { "term": "das Mittagessen", "translation": "lunch", "phonetic": "ˈmɪtaːkʔɛsn̩", "metadata": { "gender": "neuter", "plural": "Mittagessen", "pos": "noun" } },
  { "term": "das Abendessen", "translation": "dinner", "phonetic": "ˈaːbn̩tʔɛsn̩", "metadata": { "gender": "neuter", "plural": "Abendessen", "pos": "noun" } },
  { "term": "essen", "translation": "to eat", "phonetic": "ˈɛsn̩", "metadata": { "pos": "verb" } },
  { "term": "trinken", "translation": "to drink", "phonetic": "ˈtʁɪŋkn̩", "metadata": { "pos": "verb" } },
  { "term": "lecker", "translation": "tasty; delicious", "phonetic": "ˈlɛkɐ", "metadata": { "pos": "adjective" } }
]
